pyramid_customerio/__init__.py
pyramid_customerio/consumer.py
pyramid_customerio/py.typed
pyramid_customerio/tests/__init__.py
pyramid_customerio/tests/test_consumers.py
pyramid_customerio/tests/test_functional.py
pyramid_customerio/tests/test_track.py
pyramid_customerio/track.py
pyramid_customerio-1.0.0.dist-info/LICENSE
pyramid_customerio-1.0.0.dist-info/METADATA
pyramid_customerio-1.0.0.dist-info/WHEEL
pyramid_customerio-1.0.0.dist-info/RECORD
