Metadata-Version: 2.3
Name: pyramid_customerio
Version: 1.0.0
Summary: Opinionated Pyramid integration with Customer.io, a customer engagement platform.
License: MIT
Keywords: pyramid,customerio,pylons,web
Author: Niteo
Author-email: info@niteo.co
Requires-Python: >=3.11,<4.0
Classifier: Development Status :: 4 - Beta
Classifier: Framework :: Pyramid
Classifier: Intended Audience :: Developers
Classifier: License :: OSI Approved :: MIT License
Classifier: Programming Language :: Python :: 3
Classifier: Programming Language :: Python :: 3.11
Classifier: Programming Language :: Python :: 3.12
Classifier: Programming Language :: Python :: 3.13
Classifier: Topic :: Internet :: WWW/HTTP
Classifier: Topic :: Software Development :: Libraries :: Python Modules
Requires-Dist: customerio
Requires-Dist: pyramid
Requires-Dist: requests
Project-URL: Bug Tracker, https://github.com/teamniteo/pyramid_customerio/issues
Project-URL: Homepage, https://github.com/teamniteo/pyramid_customerio
Project-URL: Repository, https://github.com/teamniteo/pyramid_customerio
